apropos/__init__.py
apropos/src/__init__.py
apropos/src/bench/__init__.py
apropos/src/bench/base.py
apropos/src/bench/bigcodebench/main.py
apropos/src/bench/bigcodebench/single_step_dag.py
apropos/src/bench/bigcodebench/backends/danger.py
apropos/src/bench/bigcodebench/backends/docker.py
apropos/src/bench/bigcodebench/backends/modal.py
apropos/src/bench/bigcodebench/backends/shared.py
apropos/src/bench/craftax/game_dynamics.py
apropos/src/bench/craftax/game_information.py
apropos/src/bench/craftax/react.py
apropos/src/bench/craftax/test.py
apropos/src/bench/crafter/game_dynamics.py
apropos/src/bench/crafter/game_information.py
apropos/src/bench/crafter/recording_utils.py
apropos/src/bench/crafter/spin_up.sh
apropos/src/bench/crafter/test.py
apropos/src/bench/gradeschool_math/main.py
apropos/src/bench/gradeschool_math/dags/plan_execute.py
apropos/src/bench/gradeschool_math/dags/single_step.py
apropos/src/bench/hendryks_math/main.py
apropos/src/bench/hendryks_math/dags/plan_execute.py
apropos/src/bench/hendryks_math/dags/single_step.py
apropos/src/bench/swe_bench/modal_harness.py
apropos/src/bench/web_arena/reprex.py
apropos/src/core/__init__.py
apropos/src/core/lms/api_caching_fxns.py
apropos/src/core/lms/cache_init.py
apropos/src/core/lms/cost.py
apropos/src/core/lms/cost_table.py
apropos/src/core/lms/helpers.py
apropos/src/core/lms/tests/response_model.py
apropos/src/core/lms/vendors/anthropic_api.py
apropos/src/core/lms/vendors/base.py
apropos/src/core/lms/vendors/deepmind_api.py
apropos/src/core/lms/vendors/deepseek_api.py
apropos/src/core/lms/vendors/groq_api.py
apropos/src/core/lms/vendors/lambda_api.py
apropos/src/core/lms/vendors/ollama_api.py
apropos/src/core/lms/vendors/openai_api.py
apropos/src/core/lms/vendors/openai_like.py
apropos/src/core/lms/vendors/together_api.py
apropos/src/core/lms/vendors/json_structured_outputs/core.py
apropos/src/core/lms/vendors/json_structured_outputs/healing.py
apropos_ai-0.4.5.dist-info/METADATA
apropos_ai-0.4.5.dist-info/WHEEL
apropos_ai-0.4.5.dist-info/licenses/LICENSE
apropos_ai-0.4.5.dist-info/RECORD
