Metadata-Version: 2.3
Name: apropos-ai
Version: 0.4.5
Summary: Learning algorithms for production language model programs
License-File: LICENSE
Requires-Python: >=3.10
Requires-Dist: aiodocker>=0.21.0
Requires-Dist: anthropic>=0.34.1
Requires-Dist: backoff>=2.2.1
Requires-Dist: beartype>=0.18.5
Requires-Dist: build>=1.2.1
Requires-Dist: craftax>=1.4.3
Requires-Dist: craftaxlm==0.0.5
Requires-Dist: datasets>=2.20.0
Requires-Dist: diskcache>=5.6.3
Requires-Dist: docker>=7.1.0
Requires-Dist: google-generativeai>=0.7.2
Requires-Dist: groq>=0.9.0
Requires-Dist: gym>=0.26.2
Requires-Dist: instructor>=1.3.7
Requires-Dist: jax>=0.4.31
Requires-Dist: loguru>=0.7.2
Requires-Dist: mdurl>=0.1.2
Requires-Dist: modal>=0.64.49
Requires-Dist: networkx>=3.3
Requires-Dist: ollama>=0.3.3
Requires-Dist: openai>=1.37.1
Requires-Dist: optuna>=4.0.0
Requires-Dist: playwright>=1.46.0
Requires-Dist: pydantic>=2.8.2
Requires-Dist: pytest>=7.4.3
Requires-Dist: regex>=2024.7.24
Requires-Dist: ruff>=0.5.5
Requires-Dist: setuptools>=72.2.0
Requires-Dist: termcolor>=2.4.0
Requires-Dist: tiktoken>=0.7.0
Requires-Dist: together>=1.2.7
Requires-Dist: twine>=5.1.1
Requires-Dist: wheel>=0.44.0
Requires-Dist: zyk>=0.1.15
